[
  {
    "ts": "2025-06-14T20:39:22.892Z",
    "level": "error",
    "error": {
      "name": "UnknownField",
      "entity": {
        "original": {
          "metadata": {
            "tags": [
            ]
          },
          "sys": {
            "contentType": {
              "sys": {
                "type": "Link",
                "linkType": "ContentType",
                "id": "writeTest"
              }
            }
          },
          "fields": {
            "bar": {
              "en-GB": "HMS0002"
            },
            "richtf": {
              "en-GB": {
                "nodeType": "document",
                "data": {
                },
                "content": [
                  {
                    "nodeType": "paragraph",
                    "content": [
                      {
                        "nodeType": "text",
                        "value": "one ",
                        "marks": [
                        ],
                        "data": {
                        }
                      },
                      {
                        "nodeType": "text",
                        "value": "two",
                        "marks": [
                          {
                            "type": "italic"
                          }
                        ],
                        "data": {
                        }
                      },
                      {
                        "nodeType": "text",
                        "value": " ",
                        "marks": [
                        ],
                        "data": {
                        }
                      },
                      {
                        "nodeType": "hyperlink",
                        "data": {
                          "uri": "https://mitya.uk"
                        },
                        "content": [
                          {
                            "nodeType": "text",
                            "value": "three",
                            "marks": [
                            ],
                            "data": {
                            }
                          }
                        ]
                      }
                    ],
                    "data": {
                    }
                  }
                ]
              }
            }
          }
        },
        "transformed": {
          "metadata": {
            "tags": [
            ]
          },
          "sys": {
            "contentType": {
              "sys": {
                "type": "Link",
                "linkType": "ContentType",
                "id": "writeTest"
              }
            }
          },
          "fields": {
            "bar": {
              "en-GB": "HMS0002"
            },
            "richtf": {
              "en-GB": {
                "nodeType": "document",
                "data": {
                },
                "content": [
                  {
                    "nodeType": "paragraph",
                    "content": [
                      {
                        "nodeType": "text",
                        "value": "one ",
                        "marks": [
                        ],
                        "data": {
                        }
                      },
                      {
                        "nodeType": "text",
                        "value": "two",
                        "marks": [
                          {
                            "type": "italic"
                          }
                        ],
                        "data": {
                        }
                      },
                      {
                        "nodeType": "text",
                        "value": " ",
                        "marks": [
                        ],
                        "data": {
                        }
                      },
                      {
                        "nodeType": "hyperlink",
                        "data": {
                          "uri": "https://mitya.uk"
                        },
                        "content": [
                          {
                            "nodeType": "text",
                            "value": "three",
                            "marks": [
                            ],
                            "data": {
                            }
                          }
                        ]
                      }
                    ],
                    "data": {
                    }
                  }
                ]
              }
            }
          }
        }
      },
      "data": {
        "status": 422,
        "statusText": "Unprocessable Entity",
        "message": "No field with id \"richtf\" found.",
        "details": {
          "errors": [
            {
              "name": "unknown",
              "path": [
                "fields",
                "richtf"
              ]
            }
          ]
        },
        "request": {
          "url": "/spaces/59pjo18xz2lk/environments/master/entries",
          "headers": {
            "Accept": "application/json, text/plain, */*",
            "Content-Type": "application/vnd.contentful.management.v1+json",
            "X-Contentful-User-Agent": "app contentful.cli/1.15.1; feature space-import; sdk contentful-management.js/7.54.2; platform node.js/v20.11.0; os Windows/v20.11.0;",
            "CF-Sequence": "4a1f258e-92fc-407f-ab72-b6cb9ec0af70",
            "Authorization": "Bearer ...XtaL4",
            "user-agent": "node.js/v20.11.0",
            "Accept-Encoding": "gzip",
            "X-Contentful-Content-Type": "writeTest",
            "Content-Length": 482
          },
          "method": "post",
          "payloadData": "{\"metadata\":{\"tags\":[]},\"fields\":{\"bar\":{\"en-GB\":\"HMS0002\"},\"richtf\":{\"en-GB\":{\"nodeType\":\"document\",\"data\":{},\"content\":[{\"nodeType\":\"paragraph\",\"content\":[{\"nodeType\":\"text\",\"value\":\"one \",\"marks\":[],\"data\":{}},{\"nodeType\":\"text\",\"value\":\"two\",\"marks\":[{\"type\":\"italic\"}],\"data\":{}},{\"nodeType\":\"text\",\"value\":\" \",\"marks\":[],\"data\":{}},{\"nodeType\":\"hyperlink\",\"data\":{\"uri\":\"https://mitya.uk\"},\"content\":[{\"nodeType\":\"text\",\"value\":\"three\",\"marks\":[],\"data\":{}}]}],\"data\":{}}]}}}}"
        },
        "requestId": "72bfc2a4-4df0-4727-9cd0-6adec6f0738b"
      }
    }
  },
  {
    "ts": "2025-06-14T20:39:22.896Z",
    "level": "error",
    "error": {
      "name": "UnknownField",
      "entity": {
        "original": {
          "metadata": {
            "tags": [
            ]
          },
          "sys": {
            "contentType": {
              "sys": {
                "type": "Link",
                "linkType": "ContentType",
                "id": "writeTest"
              }
            }
          },
          "fields": {
            "bar": {
              "en-GB": "HMS0001"
            },
            "richtf": {
              "en-GB": {
                "nodeType": "document",
                "data": {
                },
                "content": [
                  {
                    "nodeType": "paragraph",
                    "content": [
                      {
                        "nodeType": "text",
                        "value": "one two three",
                        "marks": [
                        ],
                        "data": {
                        }
                      }
                    ],
                    "data": {
                    }
                  }
                ]
              }
            }
          }
        },
        "transformed": {
          "metadata": {
            "tags": [
            ]
          },
          "sys": {
            "contentType": {
              "sys": {
                "type": "Link",
                "linkType": "ContentType",
                "id": "writeTest"
              }
            }
          },
          "fields": {
            "bar": {
              "en-GB": "HMS0001"
            },
            "richtf": {
              "en-GB": {
                "nodeType": "document",
                "data": {
                },
                "content": [
                  {
                    "nodeType": "paragraph",
                    "content": [
                      {
                        "nodeType": "text",
                        "value": "one two three",
                        "marks": [
                        ],
                        "data": {
                        }
                      }
                    ],
                    "data": {
                    }
                  }
                ]
              }
            }
          }
        }
      },
      "data": {
        "status": 422,
        "statusText": "Unprocessable Entity",
        "message": "No field with id \"richtf\" found.",
        "details": {
          "errors": [
            {
              "name": "unknown",
              "path": [
                "fields",
                "richtf"
              ]
            }
          ]
        },
        "request": {
          "url": "/spaces/59pjo18xz2lk/environments/master/entries",
          "headers": {
            "Accept": "application/json, text/plain, */*",
            "Content-Type": "application/vnd.contentful.management.v1+json",
            "X-Contentful-User-Agent": "app contentful.cli/1.15.1; feature space-import; sdk contentful-management.js/7.54.2; platform node.js/v20.11.0; os Windows/v20.11.0;",
            "CF-Sequence": "4a1f258e-92fc-407f-ab72-b6cb9ec0af70",
            "Authorization": "Bearer ...XtaL4",
            "user-agent": "node.js/v20.11.0",
            "Accept-Encoding": "gzip",
            "X-Contentful-Content-Type": "writeTest",
            "Content-Length": 238
          },
          "method": "post",
          "payloadData": "{\"metadata\":{\"tags\":[]},\"fields\":{\"bar\":{\"en-GB\":\"HMS0001\"},\"richtf\":{\"en-GB\":{\"nodeType\":\"document\",\"data\":{},\"content\":[{\"nodeType\":\"paragraph\",\"content\":[{\"nodeType\":\"text\",\"value\":\"one two three\",\"marks\":[],\"data\":{}}],\"data\":{}}]}}}}"
        },
        "requestId": "2cc009cb-7bc0-4286-a53a-9c4c5b35efc4"
      }
    }
  }
]